libmath/__init__.py
libmath-1.0.2.dist-info/LICENSE
libmath-1.0.2.dist-info/METADATA
libmath-1.0.2.dist-info/WHEEL
libmath-1.0.2.dist-info/top_level.txt
libmath-1.0.2.dist-info/RECORD
