Metadata-Version: 2.1
Name: libmath
Version: 1.0.2
Summary: A Python library for math.
Home-page: https://github.com/Marko2155/libmath
Author: Marko Camandioti
Author-email: camandiotimarko@gmail.com
License: MIT
Project-URL: Documentation, https://github.com/Marko2155/libmath#readme
Project-URL: Source, https://github.com/Marko2155/libmath
Project-URL: Tracker, https://github.com/Marko2155/libmath/issues
Keywords: math,maths
License-File: LICENSE
